kapt_ads/__init__.py
kapt_ads/admin.py
kapt_ads/apps.py
kapt_ads/conf/__init__.py
kapt_ads/conf/settings.py
kapt_ads/contrib/__init__.py
kapt_ads/contrib/cmsplugin_ads/__init__.py
kapt_ads/contrib/cmsplugin_ads/apps.py
kapt_ads/contrib/cmsplugin_ads/cms_plugins.py
kapt_ads/contrib/cmsplugin_ads/conf/settings.py
kapt_ads/contrib/cmsplugin_ads/migrations/0001_initial.py
kapt_ads/contrib/cmsplugin_ads/migrations/0002_alter_adspluginconf_template.py
kapt_ads/contrib/cmsplugin_ads/migrations/__init__.py
kapt_ads/contrib/cmsplugin_ads/models.py
kapt_ads/contrib/cmsplugin_ads/receivers.py
kapt_ads/contrib/cmsplugin_ads/templates/cmsplugin_ads/ads.html
kapt_ads/fields.py
kapt_ads/forms.py
kapt_ads/locale/fr/LC_MESSAGES/django.mo
kapt_ads/locale/fr/LC_MESSAGES/django.po
kapt_ads/managers.py
kapt_ads/migrations/0001_initial.py
kapt_ads/migrations/0002_alter_ad_text.py
kapt_ads/migrations/0003_location_rename_date_end_ad_publication_date_end_and_more.py
kapt_ads/migrations/0004_alter_ad_managers_location_identifier_and_more.py
kapt_ads/migrations/0005_alter_ad_publication_date_end_and_more.py
kapt_ads/migrations/__init__.py
kapt_ads/models.py
kapt_ads/receivers.py
kapt_ads/signals.py
kapt_ads/static/django_quill/django_quill.css
kapt_ads/templates/kapt_ads/ads.html
kapt_ads/templatetags/__init__.py
kapt_ads/templatetags/ads_tags.py
kapt_ads/urls.py
kapt_ads/views.py
kapt_ads/widgets.py
kapt_ads-0.1.0.dist-info/LICENSE
kapt_ads-0.1.0.dist-info/METADATA
kapt_ads-0.1.0.dist-info/WHEEL
kapt_ads-0.1.0.dist-info/RECORD
