Metadata-Version: 2.1
Name: kapt_ads
Version: 0.1.0
Summary: 
Home-page: https://gitlab.com/kapt/open-source/kapt_ads
License: MIT
Author: Kapt dev team
Author-email: dev@kapt.mobi
Requires-Python: >=3.8,<4.0
Classifier: License :: OSI Approved :: MIT License
Classifier: Programming Language :: Python :: 3
Classifier: Programming Language :: Python :: 3.8
Classifier: Programming Language :: Python :: 3.9
Classifier: Programming Language :: Python :: 3.10
Classifier: Programming Language :: Python :: 3.11
Classifier: Programming Language :: Python :: 3.12
Classifier: Programming Language :: Python :: 3.13
Requires-Dist: Django (>=4.2,<5.0)
Requires-Dist: django-quill-editor (>=0.1.42,<0.2.0)
Project-URL: Repository, https://gitlab.com/kapt/open-source/kapt_ads
